pythonanywhere_core/__init__.py
pythonanywhere_core/base.py
pythonanywhere_core/exceptions.py
pythonanywhere_core/files.py
pythonanywhere_core/resources.py
pythonanywhere_core/schedule.py
pythonanywhere_core/students.py
pythonanywhere_core/webapp.py
pythonanywhere_core/website.py
pythonanywhere_core-0.2.9.dist-info/METADATA
pythonanywhere_core-0.2.9.dist-info/WHEEL
pythonanywhere_core-0.2.9.dist-info/licenses/LICENSE
pythonanywhere_core-0.2.9.dist-info/RECORD
